[ {
  "buildOrder" : 218,
  "reportUrl" : "https://Nat754.github.io/PulseWave/218/",
  "reportName" : "Allure Report with history",
  "data" : {
    "duration" : 738611
  }
}, {
  "buildOrder" : 226,
  "reportUrl" : "https://Nat754.github.io/PulseWave/226/",
  "reportName" : "Allure Report with history",
  "data" : {
    "duration" : 831353
  }
}, {
  "buildOrder" : 226,
  "reportUrl" : "https://Nat754.github.io/PulseWave/226/",
  "reportName" : "Allure Report with history",
  "data" : {
    "duration" : 894761
  }
}, {
  "buildOrder" : 217,
  "reportUrl" : "https://Nat754.github.io/PulseWave/217/",
  "reportName" : "Allure Report with history",
  "data" : {
    "duration" : 1153795
  }
}, {
  "buildOrder" : 216,
  "reportUrl" : "https://Nat754.github.io/PulseWave/216/",
  "reportName" : "Allure Report with history",
  "data" : {
    "duration" : 1098089
  }
}, {
  "buildOrder" : 215,
  "reportUrl" : "https://Nat754.github.io/PulseWave/215/",
  "reportName" : "Allure Report with history",
  "data" : {
    "duration" : 861438
  }
}, {
  "buildOrder" : 214,
  "reportUrl" : "https://Nat754.github.io/PulseWave/214/",
  "reportName" : "Allure Report with history",
  "data" : {
    "duration" : 896418
  }
}, {
  "buildOrder" : 213,
  "reportUrl" : "https://Nat754.github.io/PulseWave/213/",
  "reportName" : "Allure Report with history",
  "data" : {
    "duration" : 951617
  }
}, {
  "buildOrder" : 212,
  "reportUrl" : "https://Nat754.github.io/PulseWave/212/",
  "reportName" : "Allure Report with history",
  "data" : {
    "duration" : 964290
  }
}, {
  "buildOrder" : 211,
  "reportUrl" : "https://Nat754.github.io/PulseWave/211/",
  "reportName" : "Allure Report with history",
  "data" : {
    "duration" : 892378
  }
}, {
  "buildOrder" : 210,
  "reportUrl" : "https://Nat754.github.io/PulseWave/210/",
  "reportName" : "Allure Report with history",
  "data" : {
    "duration" : 876441
  }
}, {
  "buildOrder" : 225,
  "reportUrl" : "https://Nat754.github.io/PulseWave/225/",
  "reportName" : "Allure Report with history",
  "data" : {
    "duration" : 1082192
  }
}, {
  "buildOrder" : 209,
  "reportUrl" : "https://Nat754.github.io/PulseWave/209/",
  "reportName" : "Allure Report with history",
  "data" : {
    "duration" : 1775136
  }
}, {
  "buildOrder" : 209,
  "reportUrl" : "https://Nat754.github.io/PulseWave/209/",
  "reportName" : "Allure Report with history",
  "data" : {
    "duration" : 1149892
  }
}, {
  "buildOrder" : 208,
  "reportUrl" : "https://Nat754.github.io/PulseWave/208/",
  "reportName" : "Allure Report with history",
  "data" : {
    "duration" : 986812
  }
}, {
  "buildOrder" : 207,
  "reportUrl" : "https://Nat754.github.io/PulseWave/207/",
  "reportName" : "Allure Report with history",
  "data" : {
    "duration" : 1185810
  }
}, {
  "buildOrder" : 206,
  "reportUrl" : "https://Nat754.github.io/PulseWave/206/",
  "reportName" : "Allure Report with history",
  "data" : {
    "duration" : 938184
  }
}, {
  "buildOrder" : 205,
  "reportUrl" : "https://Nat754.github.io/PulseWave/205/",
  "reportName" : "Allure Report with history",
  "data" : {
    "duration" : 960819
  }
}, {
  "buildOrder" : 204,
  "reportUrl" : "https://Nat754.github.io/PulseWave/204/",
  "reportName" : "Allure Report with history",
  "data" : {
    "duration" : 1045585
  }
}, {
  "buildOrder" : 203,
  "reportUrl" : "https://Nat754.github.io/PulseWave/203/",
  "reportName" : "Allure Report with history",
  "data" : {
    "duration" : 1187839
  }
} ]